setup.cfg
setup.py
mentord/__init__.py
mentord/client.py
mentord/httpc.py
mentord.egg-info/PKG-INFO
mentord.egg-info/SOURCES.txt
mentord.egg-info/dependency_links.txt
mentord.egg-info/top_level.txt
mentord/classes/channel.py
mentord/classes/guild.py
mentord/classes/member.py
mentord/classes/message.py
mentord/classes/user.py
mentord/events/eon_message.py
mentord/events/eon_ready.py
mentord/utils/channel_opers.py