Metadata-Version: 2.1
Name: mentord
Version: 1.2.0
Summary: A sync library for creating self bots in python!
